{
  "1": [
    0,
    1,
    13,
    0,
    0,
    "2025-09-11T02:16:17Z"
  ],
  "2": [
    0,
    1,
    13,
    0,
    0,
    "2025-09-11T02:11:17Z"
  ],
  "3": [
    0,
    1,
    13,
    0,
    0,
    "2025-09-11T02:06:17Z"
  ],
  "4": [
    0,
    1,
    13,
    0,
    0,
    "2025-09-11T02:01:17Z"
  ],
  "5": [
    0,
    1,
    13,
    0,
    0,
    "2025-09-11T01:56:17Z"
  ],
  "6": [
    0,
    1,
    13,
    0,
    0,
    "2025-09-11T01:51:17Z"
  ],
  "7": [
    0,
    1,
    13,
    0,
    0,
    "2025-09-11T01:46:17Z"
  ],
  "8": [
    0,
    1,
    13,
    0,
    0,
    "2025-09-11T01:41:17Z"
  ],
  "9": [
    0,
    1,
    13,
    0,
    0,
    "2025-09-11T01:36:17Z"
  ],
  "10": [
    0,
    1,
    13,
    0,
    0,
    "2025-09-11T01:31:17Z"
  ],
  "11": [
    0,
    1,
    13,
    0,
    0,
    "2025-09-11T01:26:17Z"
  ],
  "12": [
    0,
    1,
    13,
    0,
    0,
    "2025-09-11T01:21:17Z"
  ],
  "13": [
    0,
    1,
    13,
    0,
    0,
    "2025-09-11T01:16:17Z"
  ],
  "14": [
    0,
    1,
    13,
    0,
    0,
    "2025-09-11T01:11:17Z"
  ],
  "15": [
    0,
    1,
    13,
    0,
    0,
    "2025-09-11T01:06:17Z"
  ],
  "16": [
    0,
    1,
    13,
    0,
    0,
    "2025-09-11T01:01:17Z"
  ],
  "17": [
    0,
    1,
    13,
    0,
    0,
    "2025-09-11T00:56:17Z"
  ],
  "18": [
    0,
    1,
    13,
    0,
    0,
    "2025-09-11T00:51:17Z"
  ],
  "19": [
    0,
    1,
    12,
    0,
    0,
    "2025-09-11T00:46:17Z"
  ],
  "20": [
    0,
    1,
    12,
    0,
    0,
    "2025-09-11T00:41:17Z"
  ],
  "21": [
    0,
    1,
    12,
    0,
    0,
    "2025-09-11T00:36:17Z"
  ],
  "22": [
    0,
    1,
    12,
    0,
    0,
    "2025-09-11T00:31:17Z"
  ],
  "23": [
    0,
    1,
    12,
    0,
    0,
    "2025-09-11T00:26:17Z"
  ],
  "IMEI": "866840071230108",
  "IMSI": "505016007188910",
  "Model": "CPL03-CB",
  "work mode": 2,
  "calc flag": 0,
  "count_mode": 1,
  "tdc send flag": 1,
  "count time1": 13,
  "count time2": 0,
  "count time3": 0,
  "battery": 3.56,
  "signal": 20,
  "time": "2025-09-11T02:16:56Z",
  "latitude": 0,
  "longitude": 0,
  "gps_time": "1970-01-01T00:00:00Z"
}
